distribeauty/Binomialdistribution.py
distribeauty/Gaussiandistribution.py
distribeauty/Generaldistribution.py
distribeauty/__init__.py
distribeauty/test.py
distribeauty-1.0.5.dist-info/METADATA
distribeauty-1.0.5.dist-info/WHEEL
distribeauty-1.0.5.dist-info/top_level.txt
distribeauty-1.0.5.dist-info/RECORD
