Metadata-Version: 2.1
Name: distribeauty
Version: 1.0.5
Summary: Gaussian and Binomial distributions
Home-page: UNKNOWN
Author: Bexultan Alimzhanov
Author-email: bexultan.alimzhanov@nu.edu.kz
License: UNKNOWN
Platform: UNKNOWN
